llm_tap/__init__.py
llm_tap/llm.py
llm_tap/models.py
llm_tap/to_mermaid.py
llm_tap-0.1.0.dist-info/licenses/LICENSE
llm_tap-0.1.0.dist-info/METADATA
llm_tap-0.1.0.dist-info/WHEEL
llm_tap-0.1.0.dist-info/top_level.txt
llm_tap-0.1.0.dist-info/RECORD
