Metadata-Version: 2.4
Name: llm-tap
Version: 0.1.0
Summary: lightweight library for building Trigger-Action programs with llm
Home-page: https://github.com/advanced-stack/llm-tap
Author: P.A. SCHEMBRI
Author-email: pa.schembri@advanced-stack.com
License: MIT
License-File: LICENSE
Requires-Dist: llama-cpp-python
Requires-Dist: requests
Dynamic: author
Dynamic: author-email
Dynamic: description
Dynamic: description-content-type
Dynamic: home-page
Dynamic: license
Dynamic: license-file
Dynamic: requires-dist
Dynamic: summary
